{"name":"Delete User Data","id":"reqresin;delete-user-data","testSteps":[{"number":1,"description":"When user send DELETE to reqresin with user id is 2","duration":573,"startTime":"2022-06-20T01:13:21.238+07:00[Asia/Bangkok]","result":"SUCCESS","precondition":false,"level":0,"children":[{"number":2,"description":"DELETE https://reqres.in/api/users/2\r","duration":0,"startTime":"2022-06-20T01:13:21.806+07:00[Asia/Bangkok]","result":"SUCCESS","restQuery":{"method":"DELETE","path":"https://reqres.in/api/users/2\r","content":"\r","contentType":"null","requestHeaders":"Accept\u003d*/*\r","requestCookies":"\r","responseHeaders":"Date: Sun, 19 Jun 2022 18:13:21 GMT\r\nContent-Length: 0\r\nConnection: keep-alive\r\nX-Powered-By: Express\r\nAccess-Control-Allow-Origin: *\r\nEtag: W/\"2-vyGp6PvFo4RvsFtPoIWeCReyIC8\"\r\nVia: 1.1 vegur\r\nCF-Cache-Status: DYNAMIC\r\nExpect-CT: max-age\u003d604800, report-uri\u003d\"https://report-uri.cloudflare.com/cdn-cgi/beacon/expect-ct\"\r\nReport-To: {\"endpoints\":[{\"url\":\"https:\\/\\/a.nel.cloudflare.com\\/report\\/v3?s\u003dJc%2BliV66JCzTn4uihvsZvNjqCCzMaLDFnHEiPf5TC%2Fv41%2F53oIkhmVIhkuhIZGqTpBZuzy8HS4lRVQlmsA8Z0OpnxLctNNReLez46dDgpnRNg8rs2ZSO3gx9tQ%3D%3D\"}],\"group\":\"cf-nel\",\"max_age\":604800}\r\nNEL: {\"success_fraction\":0,\"report_to\":\"cf-nel\",\"max_age\":604800}\r\nServer: cloudflare\r\nCF-RAY: 71de3cf99cf98802-SIN\r","responseCookies":"\r","statusCode":204},"precondition":false,"level":1}]},{"number":3,"description":"Then response status code should be 204","duration":7,"startTime":"2022-06-20T01:13:21.814+07:00[Asia/Bangkok]","result":"SUCCESS","precondition":false,"level":0}],"userStory":{"id":"reqresin","storyName":"Reqresin","path":"reqresin/reqresin.feature","type":"feature"},"featureTag":{"name":"Reqresin/Reqresin","type":"feature","displayName":"Reqresin/Reqresin"},"title":"Delete User Data","description":"","tags":[{"name":"delete","type":"tag","displayName":"delete"},{"name":"Reqresin","type":"capability","displayName":"Reqresin"},{"name":"Reqresin/Reqresin","type":"feature","displayName":"Reqresin"},{"name":"reqresin","type":"tag","displayName":"reqresin"}],"startTime":"2022-06-20T01:13:21.234+07:00[Asia/Bangkok]","duration":589,"projectKey":"","isManualTestingUpToDate":false,"manual":false,"testSource":"Cucumber","result":"SUCCESS"}